pixee/_version.py
pixee/cli.py
pixee/logo.py
pixee-0.8.15.dist-info/LICENSE
pixee-0.8.15.dist-info/METADATA
pixee-0.8.15.dist-info/WHEEL
pixee-0.8.15.dist-info/entry_points.txt
pixee-0.8.15.dist-info/top_level.txt
pixee-0.8.15.dist-info/RECORD
