Metadata-Version: 2.1
Name: pixee
Version: 0.8.15
Summary: Pixee CLI
Author-email: Pixee <python@pixee.ai>
License: GNU AFFERO GENERAL PUBLIC LICENSE
Project-URL: Homepage, https://pixee.ai
Requires-Python: >=3.10.0
License-File: LICENSE
Requires-Dist: codemodder ==0.100.0
Requires-Dist: click
Requires-Dist: prompt-toolkit
Requires-Dist: questionary ~=2.0.0
Requires-Dist: security ~=1.2.0
Provides-Extra: dev
Requires-Dist: black ; extra == 'dev'
Requires-Dist: pre-commit ; extra == 'dev'
Requires-Dist: pylint ; extra == 'dev'
Requires-Dist: pytest ; extra == 'dev'
Requires-Dist: pytest-cov ; extra == 'dev'
Requires-Dist: pytest-mock ; extra == 'dev'
